quartz_cron_checker/__init__.py
quartz_cron_checker/checker.py
quartz_cron_checker/constants.py
quartz_cron_checker/exceptions.py
quartz_cron_checker/field_configs.py
quartz_cron_checker/parsers.py
quartz_cron_checker/validators.py
quartz_cron_checker-0.2.1.dist-info/licenses/LICENSE
quartz_cron_checker-0.2.1.dist-info/METADATA
quartz_cron_checker-0.2.1.dist-info/WHEEL
quartz_cron_checker-0.2.1.dist-info/top_level.txt
quartz_cron_checker-0.2.1.dist-info/RECORD
