Metadata-Version: 2.4
Name: quartz-cron-checker
Version: 0.2.1
Summary: Simple Python library to check if a Quartz cron expression is valid.
Author-email: Jessica Smith <j.smith.git1@gmail.com>
Requires-Python: >=3.10
License-File: LICENSE
Dynamic: license-file
